MANIFEST.in
README.rst
setup.py
coop/__init__.py
coop/admin.py
coop/base_admin.py
coop/base_models.py
coop/context_processors.py
coop/coop_bar_cfg.py
coop/data_urls.py
coop/db_settings.py
coop/debug_settings.py
coop/default_project_settings.py
coop/default_project_urls.py
coop/feeds.py
coop/forms.py
coop/minimal_settings.py
coop/models.py
coop/search_indexes.py
coop/settings.py
coop/signals.py
coop/tests.py
coop/urls.py
coop/views.py
coop/agenda/__init__.py
coop/agenda/admin.py
coop/agenda/context_processors.py
coop/agenda/forms.py
coop/agenda/models.py
coop/agenda/tests.py
coop/agenda/urls.py
coop/agenda/utils.py
coop/agenda/views.py
coop/agenda/conf/__init__.py
coop/agenda/conf/agenda_settings.py
coop/agenda/locale/de/LC_MESSAGES/django.mo
coop/agenda/locale/de/LC_MESSAGES/django.po
coop/agenda/locale/fr/LC_MESSAGES/django.mo
coop/agenda/locale/fr/LC_MESSAGES/django.po
coop/article/__init__.py
coop/article/admin.py
coop/article/models.py
coop/article/locale/fr/LC_MESSAGES/django.mo
coop/article/locale/fr/LC_MESSAGES/django.po
coop/bin/__init__.py
coop/bin/coop-admin.py
coop/bin/runinenv.sh
coop/doc/__init__.py
coop/doc/admin.py
coop/doc/models.py
coop/doc/urls.py
coop/doc/views.py
coop/doc/locale/fr/LC_MESSAGES/django.mo
coop/doc/locale/fr/LC_MESSAGES/django.po
coop/exchange/__init__.py
coop/exchange/admin.py
coop/exchange/models.py
coop/exchange/tests.py
coop/exchange/urls.py
coop/exchange/views.py
coop/exchange/locale/fr/LC_MESSAGES/django.mo
coop/exchange/locale/fr/LC_MESSAGES/django.po
coop/fabfile/fab_templates/vhost.txt
coop/fabfile/fab_templates/wsgi.txt
coop/link/__init__.py
coop/link/admin.py
coop/link/models.py
coop/link/locale/fr/LC_MESSAGES/django.mo
coop/link/locale/fr/LC_MESSAGES/django.po
coop/mailing/__init__.py
coop/mailing/admin.py
coop/mailing/coop_bar_links.py
coop/mailing/forms.py
coop/mailing/models.py
coop/mailing/signals.py
coop/mailing/soap.py
coop/mailing/urls.py
coop/mailing/utils.py
coop/mailing/views.py
django_coop.egg-info/PKG-INFO
django_coop.egg-info/SOURCES.txt
django_coop.egg-info/dependency_links.txt
django_coop.egg-info/not-zip-safe
django_coop.egg-info/top_level.txt