Metadata-Version: 1.0
Name: django-coop
Version: 0.7.3
Summary: A basis for a cooperative organization directory, with people, organization, offers.
Home-page: https://github.com/quinode/django-coop/
Author: Cooperative Quinode
Author-email: contact@quinode.fr
License: BSD
Download-URL: https://github.com/quinode/django-coop/tarball/master
Platform: UNKNOWN
Classifier: Development Status :: 4 - Beta
Classifier: Environment :: Web Environment
Classifier: Intended Audience :: Developers
Classifier: License :: OSI Approved :: BSD License
Classifier: Operating System :: OS Independent
Classifier: Programming Language :: Python
Classifier: Framework :: Django
Classifier: Natural Language :: English
Classifier: Natural Language :: French
Classifier: Topic :: Internet :: WWW/HTTP :: Dynamic Content
Classifier: Topic :: Internet :: WWW/HTTP :: WSGI :: Application
